ConstrainedKmeansCluster/__init__.py
ConstrainedKmeansCluster/weighted_mm_kmeans.py
ConstrainedKmeansCluster-0.0.4.dist-info/METADATA
ConstrainedKmeansCluster-0.0.4.dist-info/WHEEL
ConstrainedKmeansCluster-0.0.4.dist-info/top_level.txt
ConstrainedKmeansCluster-0.0.4.dist-info/RECORD
